pyprik/__init__.py
pyprik/agent/__init__.py
pyprik/agent/serveragent.py
pyprik/src/__init__.py
pyprik/src/llm_agent.py
pyprik/src/pyprik.py
pyprik/src/server_agent.py
pyprik-0.2.1.dist-info/licenses/LICENSE.txt
pyprik-0.2.1.dist-info/METADATA
pyprik-0.2.1.dist-info/WHEEL
pyprik-0.2.1.dist-info/top_level.txt
pyprik-0.2.1.dist-info/RECORD
