Metadata-Version: 2.4
Name: pyprik
Version: 0.2.1
Summary: Intelligent data matching library with LLM-powered natural language responses
Home-page: https://github.com/pruthvikmachhi/pyprik
Author: Pruthvik
Author-email: pruthvikmachhi7@gmail.com
License: MIT
Project-URL: Bug Reports, https://github.com/pruthvikmachhi/pyprik/issues
Project-URL: Source, https://github.com/pruthvikmachhi/pyprik
Project-URL: Documentation, https://github.com/pruthvikmachhi/pyprik#readme
Keywords: data matching,search,llm,ai,natural language,fastapi
Classifier: Development Status :: 4 - Beta
Classifier: Intended Audience :: Developers
Classifier: License :: OSI Approved :: MIT License
Classifier: Programming Language :: Python :: 3.8
Classifier: Programming Language :: Python :: 3.9
Classifier: Programming Language :: Python :: 3.10
Classifier: Programming Language :: Python :: 3.11
Classifier: Programming Language :: Python :: 3.12
Classifier: Operating System :: OS Independent
Classifier: Topic :: Software Development :: Libraries :: Python Modules
Classifier: Topic :: Scientific/Engineering :: Artificial Intelligence
Classifier: Topic :: Text Processing :: Linguistic
Requires-Python: >=3.8
License-File: LICENSE.txt
Requires-Dist: pandas>=2.1.4
Requires-Dist: fastapi>=0.104.0
Requires-Dist: uvicorn>=0.24.0
Requires-Dist: pydantic>=2.0.0
Requires-Dist: openai>=1.0.0
Requires-Dist: google-generativeai>=0.3.0
Provides-Extra: dev
Requires-Dist: pytest>=8.2.2; extra == "dev"
Requires-Dist: twine>=5.1.1; extra == "dev"
Dynamic: author
Dynamic: author-email
Dynamic: classifier
Dynamic: description
Dynamic: description-content-type
Dynamic: home-page
Dynamic: keywords
Dynamic: license
Dynamic: license-file
Dynamic: project-url
Dynamic: provides-extra
Dynamic: requires-dist
Dynamic: requires-python
Dynamic: summary
